MDInteractions/__init__.py
MDInteractions/cli.py
MDInteractions/mean_cli.py
MDInteractions/mean_distance.py
MDInteractions/protein_interactions.py
MDInteractions-1.1.0.dist-info/LICENSE.txt
MDInteractions-1.1.0.dist-info/METADATA
MDInteractions-1.1.0.dist-info/WHEEL
MDInteractions-1.1.0.dist-info/entry_points.txt
MDInteractions-1.1.0.dist-info/top_level.txt
MDInteractions-1.1.0.dist-info/RECORD
