Metadata-Version: 2.1
Name: MDInteractions
Version: 1.1.0
Summary: A python package for the distance-based analysis of intra- and inter-protein interactions
Home-page: https://github.com/afowdar/MDInteractions
Author: Anjani Fowdar and Darren P Martin
Author-email: anjanifowdar@gmail.com
License: UNKNOWN
Platform: UNKNOWN
Classifier: Programming Language :: Python :: 3.10
Classifier: Programming Language :: Python :: 3.11
Classifier: Programming Language :: Python :: 3.12
Classifier: Operating System :: OS Independent
Classifier: License :: OSI Approved :: MIT License
Classifier: Development Status :: 5 - Production/Stable
Classifier: Intended Audience :: Science/Research
Classifier: Intended Audience :: Developers
Classifier: Topic :: Scientific/Engineering :: Chemistry
Classifier: Topic :: Scientific/Engineering :: Bio-Informatics
Classifier: Topic :: Software Development :: Libraries :: Python Modules
Requires-Python: >=3.10
License-File: LICENSE.txt
Requires-Dist: MDAnalysis
Requires-Dist: numpy
Requires-Dist: pandas
